LICENSE
README.md
setup.py
circuit_dawg/__init__.py
circuit_dawg/dawgs.py
circuit_dawg/units.py
circuit_dawg/wrapper.py
circuit_dawg.egg-info/PKG-INFO
circuit_dawg.egg-info/SOURCES.txt
circuit_dawg.egg-info/dependency_links.txt
circuit_dawg.egg-info/top_level.txt