Metadata-Version: 2.1
Name: circuit-dawg
Version: 1.0.1
Summary: Pure-python reader for DAWGs (DAFSAs) that were created by dawgdic C++ library or the DAWG Python library. Optimized to run on CircuitPython.
Home-page: https://github.com/kbravh/circuit-dawg/
Author: Karey Higuera
Author-email: karey.higuera@gmail.com
License: UNKNOWN
Keywords: circuitPython,DAWG,DAFSA,word list
Platform: UNKNOWN
Classifier: Development Status :: 4 - Beta
Classifier: Intended Audience :: Developers
Classifier: Intended Audience :: Science/Research
Classifier: License :: OSI Approved :: MIT License
Classifier: Programming Language :: Python
Classifier: Programming Language :: Python :: Implementation :: MicroPython
Classifier: Topic :: Software Development :: Libraries :: Python Modules
Classifier: Topic :: Scientific/Engineering :: Information Analysis
Classifier: Topic :: Text Processing :: Linguistic
